{
  "db_name": "PostgreSQL",
  "query": "\n        SELECT device_id, device_name, last_name_updated_at\n        FROM devices\n        WHERE device_id = $1\n        ",
  "describe": {
    "columns": [
      {
        "ordinal": 0,
        "name": "device_id",
        "type_info": "Uuid"
      },
      {
        "ordinal": 1,
        "name": "device_name",
        "type_info": "Varchar"
      },
      {
        "ordinal": 2,
        "name": "last_name_updated_at",
        "type_info": "Timestamptz"
      }
    ],
    "parameters": {
      "Left": [
        "Uuid"
      ]
    },
    "nullable": [
      false,
      false,
      true
    ]
  },
  "hash": "ee7b9f223b78d2ed95be0d7cda368c4055fb3feae531990b5cf7db324caf9d02"
}
